datasette_enrichments_llm/__init__.py
datasette_enrichments_llm-0.1a2.dist-info/licenses/LICENSE
datasette_enrichments_llm-0.1a2.dist-info/METADATA
datasette_enrichments_llm-0.1a2.dist-info/WHEEL
datasette_enrichments_llm-0.1a2.dist-info/entry_points.txt
datasette_enrichments_llm-0.1a2.dist-info/top_level.txt
datasette_enrichments_llm-0.1a2.dist-info/RECORD
