Metadata-Version: 2.4
Name: datasette-enrichments-llm
Version: 0.1a2
Summary: Enrich data by prompting LLMs
Author: Simon Willison
License-Expression: Apache-2.0
Project-URL: Homepage, https://github.com/datasette/datasette-enrichments-llm
Project-URL: Changelog, https://github.com/datasette/datasette-enrichments-llm/releases
Project-URL: Issues, https://github.com/datasette/datasette-enrichments-llm/issues
Project-URL: CI, https://github.com/datasette/datasette-enrichments-llm/actions
Classifier: Framework :: Datasette
Requires-Python: >=3.10
License-File: LICENSE
Requires-Dist: datasette>=1.0a21
Requires-Dist: llm>=0.19.1
Requires-Dist: datasette-enrichments
Provides-Extra: test
Requires-Dist: pytest; extra == "test"
Requires-Dist: pytest-asyncio; extra == "test"
Requires-Dist: pytest-recording; extra == "test"
Dynamic: license-file
